{
    "icon": "fa-openshift",
    "title": "使用CLI来管理资源对象",
    "description": "",
    "pathwayTitle": "OpenShift",
    "difficulty": "beginner",
    "time": "10-15 minutes",
    "backend": {
        "imageid": "openshift-4-4"
    },
    "environment": {
        "showdashboard": true,
        "dashboards": [
            {
                "name": "Console",
                "href": "https://console-openshift-console-[[HOST_SUBDOMAIN]]-443-[[KATACODA_HOST]].environments.katacoda.com"
            }
        ],
        "uilayout": "terminal-iframe"
    },
    "details": {
        "steps": [
            {
                "title": "主题1 - 部署应用程序",
                "text": "01-deploying-an-application.md"
            },
            {
                "title": "主题2 - 资源对象类型",
                "text": "02-resource-object-types.md"
            },
            {
                "title": "主题3 - 查询资源对象",
                "text": "03-querying-resource-objects.md"
            },
            {
                "title": "主题4 - 编辑资源对象",
                "text": "04-editing-resource-objects.md"
            },
            {
                "title": "主题5 - 创建资源对象",
                "text": "05-creating-resource-objects.md"
            },
            {
                "title": "主题6 - 替换资源对象",
                "text": "06-replacing-resource-objects.md"
            },
            {
                "title": "主题7 - 标记资源对象",
                "text": "07-labelling-resource-objects.md"
            },
            {
                "title": "主题8 - 删除资源对象",
                "text": "08-deleting-resource-objects.md"
            }
        ],
        "intro": {
            "text": "intro.md"
        },
        "finish": {
            "text": "finish.md"
        }
    }
}